{
  "invoice_number": "10-184-MIB-0013",
  "company_name": "COSMETICOS TRUJILLO",
  "total_usd_amount": "30864.6",
  "currency": "USD",
  "confidence_level": "HIGH",
  "extraction_notes": null,
  "amount_source_text": null,
  "client_reference": null,
  "material_description": null,
  "fecha_hora": "19/07/2024 16:46:30",
  "cantidad_total": null,
  "valor_unitario": null,
  "line_items": [
    {
      "line_number": 1,
      "sku": "10-184-MIB-0013",
      "description": "AGUA DE TOCADOR MIBHBMTC COCOPALM150ML",
      "quantity": 15828.0,
      "unit_price": "1.95",
      "line_total": "30864.6",
      "unit_of_measure": null,
      "country_of_origin": null,
      "hts_code": null
    }
  ],
  "processing_time": 26.905009746551514,
  "extraction_method": "enhanced",
  "line_item_extraction_success": true,
  "cached_at": 1749664605.4001555,
  "file_path": "data\\temp\\extraction_AE900710201\\FACTURA COMERCIAL 0550000691.pdf"
}