{
  "invoice_number": "10-184-MIB-0057",
  "company_name": "COSMETICOS TRUJILLO",
  "total_usd_amount": "23448.96",
  "currency": "USD",
  "confidence_level": "HIGH",
  "extraction_notes": null,
  "amount_source_text": null,
  "client_reference": null,
  "material_description": null,
  "fecha_hora": "31/08/2024 12:56:58",
  "cantidad_total": null,
  "valor_unitario": null,
  "line_items": [
    {
      "line_number": 1,
      "sku": "10-184-MIB-0057",
      "description": "AGUA DE TOCADOR MIB VANBOUR 75ML",
      "quantity": 19872.0,
      "unit_price": "1.18",
      "line_total": "23448.96",
      "unit_of_measure": null,
      "country_of_origin": null,
      "hts_code": null
    }
  ],
  "processing_time": 25.211910486221313,
  "extraction_method": "enhanced",
  "line_item_extraction_success": true,
  "cached_at": 1749658275.7213123,
  "file_path": "data\\temp\\extraction_AE900715465\\FACTURA COMERCIAL 0550000813.pdf"
}