{
  "invoice_number": "10-184-FIN-0011",
  "company_name": "COSMETICOS TRUJILLO",
  "total_usd_amount": "2836.8",
  "currency": "USD",
  "confidence_level": "HIGH",
  "extraction_notes": null,
  "amount_source_text": "Total USD: 2836.80",
  "client_reference": null,
  "material_description": null,
  "fecha_hora": "22/02/2025 14:35:31",
  "cantidad_total": null,
  "valor_unitario": null,
  "line_items": [
    {
      "line_number": 1,
      "sku": "10-184-FIN-0011",
      "description": "AGUA DE TOCADOR FIN IMMUSK 150 ML",
      "quantity": 1440.0,
      "unit_price": "1.97",
      "line_total": "2836.8",
      "unit_of_measure": "PCS",
      "country_of_origin": null,
      "hts_code": null
    }
  ],
  "processing_time": 26.664788722991943,
  "extraction_method": "enhanced",
  "line_item_extraction_success": true,
  "cached_at": 1749664522.0181484,
  "file_path": "data\\temp\\extraction_AE900738376\\FACTURA COMERCIAL 0550001524.pdf"
}